moveread/pipelines/game_preprocess/__init__.py
moveread/pipelines/game_preprocess/__init__.pyi
moveread/pipelines/game_preprocess/_types.py
moveread/pipelines/game_preprocess/cli.py
moveread/pipelines/game_preprocess/core.py
moveread/pipelines/game_preprocess/join.py
moveread/pipelines/game_preprocess/preinput.py
moveread/pipelines/game_preprocess/spec.py
moveread_pipelines_game_preprocess-0.5.1.dist-info/METADATA
moveread_pipelines_game_preprocess-0.5.1.dist-info/WHEEL
moveread_pipelines_game_preprocess-0.5.1.dist-info/entry_points.txt
moveread_pipelines_game_preprocess-0.5.1.dist-info/top_level.txt
moveread_pipelines_game_preprocess-0.5.1.dist-info/RECORD
